coy/__init__.py
coy/controller.py
coy/coy.py
coy/watcher.py
coy-0.0.1.dist-info/COPYING
coy-0.0.1.dist-info/METADATA
coy-0.0.1.dist-info/WHEEL
coy-0.0.1.dist-info/entry_points.txt
coy-0.0.1.dist-info/top_level.txt
coy-0.0.1.dist-info/RECORD
