Metadata-Version: 2.1
Name: coy
Version: 0.0.1
Summary: A program to control the behavior of process dynamically.
Home-page: https://bitbucket.org/nshou/coy
Author: nshou
Author-email: nshou@coronocoya.net
License: MIT
Platform: UNKNOWN
Classifier: License :: OSI Approved :: MIT License
Classifier: Programming Language :: Python :: 3
Classifier: Topic :: Utilities
